{
  "lastUpdate": "2025-09-12T23:18:54.447Z",
  "domains": [
    "ad.nl",
    "pzc.nl",
    "ed.nl",
    "bd.nl",
    "destentor.nl",
    "gelderlander.nl",
    "tubantia.nl",
    "bndestem.nl"
  ],
  "latestSnapshots": [
    {
      "domain": "ad.nl",
      "success": false,
      "timestamp": "2025-09-12T23:18:54.447Z",
      "error": "Page.captureScreenshot timed out. Increase the 'protocolTimeout' setting in launch/connect calls for a higher timeout if needed."
    },
    {
      "domain": "pzc.nl",
      "success": true,
      "snapshotId": "pzc.nl/2025-09-13/01-00",
      "timestamp": "2025-09-12T23:17:29.147Z"
    },
    {
      "domain": "ed.nl",
      "success": true,
      "snapshotId": "ed.nl/2025-09-13/01-00",
      "timestamp": "2025-09-12T23:17:29.129Z"
    },
    {
      "domain": "bd.nl",
      "success": true,
      "snapshotId": "bd.nl/2025-09-13/01-00",
      "timestamp": "2025-09-12T23:18:36.358Z"
    },
    {
      "domain": "destentor.nl",
      "success": true,
      "snapshotId": "destentor.nl/2025-09-13/01-00",
      "timestamp": "2025-09-12T23:18:36.394Z"
    },
    {
      "domain": "gelderlander.nl",
      "success": true,
      "snapshotId": "gelderlander.nl/2025-09-13/01-00",
      "timestamp": "2025-09-12T23:18:36.447Z"
    },
    {
      "domain": "tubantia.nl",
      "success": true,
      "snapshotId": "tubantia.nl/2025-09-13/01-00",
      "timestamp": "2025-09-12T23:18:46.171Z"
    },
    {
      "domain": "bndestem.nl",
      "success": true,
      "snapshotId": "bndestem.nl/2025-09-13/01-00",
      "timestamp": "2025-09-12T23:18:46.208Z"
    }
  ]
}