{
  "date": "2025-10-14",
  "snapshots": [
    {
      "time": "00-14",
      "timestamp": "2025-10-14T00:14:10+0200",
      "displayTime": "00:14",
      "domains": [
        "ad.nl",
        "pzc.nl",
        "ed.nl",
        "bd.nl",
        "destentor.nl",
        "gelderlander.nl",
        "tubantia.nl",
        "bndestem.nl"
      ]
    },
    {
      "time": "01-13",
      "timestamp": "2025-10-14T01:13:37+0200",
      "displayTime": "01:13",
      "domains": [
        "ad.nl",
        "pzc.nl",
        "ed.nl",
        "bd.nl",
        "destentor.nl",
        "gelderlander.nl",
        "tubantia.nl",
        "bndestem.nl"
      ]
    },
    {
      "time": "03-09",
      "timestamp": "2025-10-14T03:09:21+0200",
      "displayTime": "03:09",
      "domains": [
        "ad.nl",
        "pzc.nl",
        "ed.nl",
        "bd.nl",
        "destentor.nl",
        "gelderlander.nl",
        "tubantia.nl",
        "bndestem.nl"
      ]
    },
    {
      "time": "04-58",
      "timestamp": "2025-10-14T04:58:12+0200",
      "displayTime": "04:58",
      "domains": [
        "ad.nl",
        "pzc.nl",
        "ed.nl",
        "bd.nl",
        "destentor.nl",
        "gelderlander.nl",
        "tubantia.nl",
        "bndestem.nl"
      ]
    },
    {
      "time": "05-34",
      "timestamp": "2025-10-14T05:34:41+0200",
      "displayTime": "05:34",
      "domains": [
        "ad.nl",
        "pzc.nl",
        "ed.nl",
        "bd.nl",
        "destentor.nl",
        "gelderlander.nl",
        "tubantia.nl",
        "bndestem.nl"
      ]
    },
    {
      "time": "06-18",
      "timestamp": "2025-10-14T06:18:48+0200",
      "displayTime": "06:18",
      "domains": [
        "ad.nl",
        "pzc.nl",
        "ed.nl",
        "bd.nl",
        "destentor.nl",
        "gelderlander.nl",
        "tubantia.nl",
        "bndestem.nl"
      ]
    },
    {
      "time": "07-15",
      "timestamp": "2025-10-14T07:15:33+0200",
      "displayTime": "07:15",
      "domains": [
        "ad.nl",
        "pzc.nl",
        "ed.nl",
        "bd.nl",
        "destentor.nl",
        "gelderlander.nl",
        "tubantia.nl",
        "bndestem.nl"
      ]
    },
    {
      "time": "08-23",
      "timestamp": "2025-10-14T08:23:56+0200",
      "displayTime": "08:23",
      "domains": [
        "ad.nl",
        "pzc.nl",
        "ed.nl",
        "bd.nl",
        "destentor.nl",
        "gelderlander.nl",
        "tubantia.nl",
        "bndestem.nl"
      ]
    },
    {
      "time": "09-17",
      "timestamp": "2025-10-14T09:17:21+0200",
      "displayTime": "09:17",
      "domains": [
        "ad.nl",
        "pzc.nl",
        "ed.nl",
        "bd.nl",
        "destentor.nl",
        "gelderlander.nl",
        "tubantia.nl",
        "bndestem.nl"
      ]
    },
    {
      "time": "10-19",
      "timestamp": "2025-10-14T10:19:48+0200",
      "displayTime": "10:19",
      "domains": [
        "ad.nl",
        "pzc.nl",
        "ed.nl",
        "bd.nl",
        "destentor.nl",
        "gelderlander.nl",
        "tubantia.nl",
        "bndestem.nl"
      ]
    },
    {
      "time": "11-17",
      "timestamp": "2025-10-14T11:17:51+0200",
      "displayTime": "11:17",
      "domains": [
        "ad.nl",
        "pzc.nl",
        "ed.nl",
        "bd.nl",
        "destentor.nl",
        "gelderlander.nl",
        "tubantia.nl",
        "bndestem.nl"
      ]
    },
    {
      "time": "12-16",
      "timestamp": "2025-10-14T12:16:50+0200",
      "displayTime": "12:16",
      "domains": [
        "ad.nl",
        "pzc.nl",
        "ed.nl",
        "bd.nl",
        "destentor.nl",
        "gelderlander.nl",
        "tubantia.nl",
        "bndestem.nl"
      ]
    },
    {
      "time": "13-13",
      "timestamp": "2025-10-14T13:13:16+0200",
      "displayTime": "13:13",
      "domains": [
        "ad.nl",
        "pzc.nl",
        "ed.nl",
        "bd.nl",
        "destentor.nl",
        "gelderlander.nl",
        "tubantia.nl",
        "bndestem.nl"
      ]
    },
    {
      "time": "14-33",
      "timestamp": "2025-10-14T14:33:49+0200",
      "displayTime": "14:33",
      "domains": [
        "ad.nl",
        "pzc.nl",
        "ed.nl",
        "bd.nl",
        "destentor.nl",
        "gelderlander.nl",
        "tubantia.nl",
        "bndestem.nl"
      ]
    },
    {
      "time": "15-27",
      "timestamp": "2025-10-14T15:27:25+0200",
      "displayTime": "15:27",
      "domains": [
        "ad.nl",
        "pzc.nl",
        "ed.nl",
        "bd.nl",
        "destentor.nl",
        "gelderlander.nl",
        "tubantia.nl",
        "bndestem.nl"
      ]
    },
    {
      "time": "16-16",
      "timestamp": "2025-10-14T16:16:28+0200",
      "displayTime": "16:16",
      "domains": [
        "ad.nl",
        "pzc.nl",
        "ed.nl",
        "bd.nl",
        "destentor.nl",
        "gelderlander.nl",
        "tubantia.nl",
        "bndestem.nl"
      ]
    },
    {
      "time": "17-18",
      "timestamp": "2025-10-14T17:18:03+0200",
      "displayTime": "17:18",
      "domains": [
        "ad.nl",
        "pzc.nl",
        "ed.nl",
        "bd.nl",
        "destentor.nl",
        "gelderlander.nl",
        "tubantia.nl",
        "bndestem.nl"
      ]
    },
    {
      "time": "18-19",
      "timestamp": "2025-10-14T18:19:50+0200",
      "displayTime": "18:19",
      "domains": [
        "ad.nl",
        "pzc.nl",
        "ed.nl",
        "bd.nl",
        "destentor.nl",
        "gelderlander.nl",
        "tubantia.nl",
        "bndestem.nl"
      ]
    },
    {
      "time": "19-14",
      "timestamp": "2025-10-14T19:14:46+0200",
      "displayTime": "19:14",
      "domains": [
        "ad.nl",
        "pzc.nl",
        "ed.nl",
        "bd.nl",
        "destentor.nl",
        "gelderlander.nl",
        "tubantia.nl",
        "bndestem.nl"
      ]
    },
    {
      "time": "20-23",
      "timestamp": "2025-10-14T20:23:08+0200",
      "displayTime": "20:23",
      "domains": [
        "ad.nl",
        "pzc.nl",
        "ed.nl",
        "bd.nl",
        "destentor.nl",
        "gelderlander.nl",
        "tubantia.nl",
        "bndestem.nl"
      ]
    },
    {
      "time": "21-12",
      "timestamp": "2025-10-14T21:12:43+0200",
      "displayTime": "21:12",
      "domains": [
        "ad.nl",
        "pzc.nl",
        "ed.nl",
        "bd.nl",
        "destentor.nl",
        "gelderlander.nl",
        "tubantia.nl",
        "bndestem.nl"
      ]
    },
    {
      "time": "22-16",
      "timestamp": "2025-10-14T22:16:59+0200",
      "displayTime": "22:16",
      "domains": [
        "ad.nl",
        "pzc.nl",
        "ed.nl",
        "bd.nl",
        "destentor.nl",
        "gelderlander.nl",
        "tubantia.nl",
        "bndestem.nl"
      ]
    },
    {
      "time": "23-14",
      "timestamp": "2025-10-14T23:14:16+0200",
      "displayTime": "23:14",
      "domains": [
        "ad.nl",
        "pzc.nl",
        "ed.nl",
        "bd.nl",
        "destentor.nl",
        "gelderlander.nl",
        "tubantia.nl",
        "bndestem.nl"
      ]
    }
  ]
}