{
  "date": "2026-06-07",
  "snapshots": [
    {
      "time": "00-22",
      "timestamp": "2026-06-07T00:22:13+0200",
      "displayTime": "00:22",
      "domains": [
        "ad.nl",
        "pzc.nl",
        "ed.nl",
        "bd.nl",
        "destentor.nl",
        "gelderlander.nl",
        "tubantia.nl",
        "bndestem.nl"
      ]
    },
    {
      "time": "00-50",
      "timestamp": "2026-06-07T00:50:49+0200",
      "displayTime": "00:50",
      "domains": [
        "ad.nl",
        "pzc.nl",
        "ed.nl",
        "bd.nl",
        "destentor.nl",
        "gelderlander.nl",
        "tubantia.nl",
        "bndestem.nl"
      ]
    },
    {
      "time": "07-31",
      "timestamp": "2026-06-07T07:31:02+0200",
      "displayTime": "07:31",
      "domains": [
        "ad.nl",
        "pzc.nl",
        "ed.nl",
        "bd.nl",
        "destentor.nl",
        "gelderlander.nl",
        "tubantia.nl",
        "bndestem.nl"
      ]
    },
    {
      "time": "08-02",
      "timestamp": "2026-06-07T08:02:41+0200",
      "displayTime": "08:02",
      "domains": [
        "ad.nl",
        "pzc.nl",
        "ed.nl",
        "bd.nl",
        "destentor.nl",
        "gelderlander.nl",
        "tubantia.nl",
        "bndestem.nl"
      ]
    },
    {
      "time": "09-20",
      "timestamp": "2026-06-07T09:20:42+0200",
      "displayTime": "09:20",
      "domains": [
        "ad.nl",
        "pzc.nl",
        "ed.nl",
        "bd.nl",
        "destentor.nl",
        "gelderlander.nl",
        "tubantia.nl",
        "bndestem.nl"
      ]
    }
  ]
}